pyircor/__init__.py
pyircor/check.py
pyircor/permute.py
pyircor/tau.py
pyircor/tauap.py
pyircor-0.2.0.dist-info/AUTHORS.rst
pyircor-0.2.0.dist-info/LICENSE
pyircor-0.2.0.dist-info/METADATA
pyircor-0.2.0.dist-info/WHEEL
pyircor-0.2.0.dist-info/top_level.txt
pyircor-0.2.0.dist-info/RECORD
