Metadata-Version: 2.1
Name: pyircor
Version: 0.2.0
Summary: Python implementation of the R package `ircor`
Home-page: https://github.com/eldrin/pyircor
Author: Jaehun Kim
Author-email: jaehun.j.kim@gmail.com
License: MIT license
Keywords: pyircor
Platform: UNKNOWN
Classifier: Development Status :: 2 - Pre-Alpha
Classifier: Intended Audience :: Developers
Classifier: License :: OSI Approved :: MIT License
Classifier: Natural Language :: English
Classifier: Programming Language :: Python :: 3
Classifier: Programming Language :: Python :: 3.5
Classifier: Programming Language :: Python :: 3.6
Classifier: Programming Language :: Python :: 3.7
Requires-Python: >=3.5, <3.8
Requires-Dist: numpy (==1.17.4)
Requires-Dist: numba (==0.46.0)
Requires-Dist: scipy (==1.3.3)
